examples/numpy_arrays_profiling.py
examples/numpy_arrays_profiling_custom.py
examples/profiler_data/array_handler/memory_plot_array_handler_450155_data.png
memory_profiler/decorators.py
memory_profiler/src/plottrace.py
memory_profiler/src/profiler.py
memory_profiler/src/configs/config.yaml
tests/src_test.py
python_memory_profiler-0.4.4.dist-info/LICENSE
python_memory_profiler-0.4.4.dist-info/METADATA
python_memory_profiler-0.4.4.dist-info/WHEEL
python_memory_profiler-0.4.4.dist-info/top_level.txt
python_memory_profiler-0.4.4.dist-info/RECORD
