Metadata-Version: 2.2
Name: python-memory-profiler
Version: 0.4.4
Summary: A Python library for memory usage profiling and visualization.
Author-email: Ghassene Jebali <ghassene.jebali@gmail.com>
License: MIT License
Project-URL: Homepage, https://github.com/GhasseneJebali/python-memory-profiler
Project-URL: Repository, https://github.com/GhasseneJebali/python-memory-profiler
Keywords: memory,profiling,monitoring,performance,python
Classifier: Development Status :: 3 - Alpha
Classifier: Intended Audience :: Developers
Classifier: License :: OSI Approved :: MIT License
Classifier: Programming Language :: Python
Classifier: Programming Language :: Python :: 3.6
Classifier: Programming Language :: Python :: 3.7
Classifier: Programming Language :: Python :: 3.8
Classifier: Programming Language :: Python :: 3.9
Classifier: Programming Language :: Python :: 3.10
Classifier: Topic :: Software Development :: Debuggers
Classifier: Topic :: System :: Monitoring
Requires-Python: >=3.6
License-File: LICENSE
Requires-Dist: psutil
Requires-Dist: numpy
Requires-Dist: matplotlib
Requires-Dist: pyyaml
Requires-Dist: tqdm
Requires-Dist: omegaconf
Requires-Dist: pytest
